{
  "schemaVersion": 1,
  "id": "trident-fly",
  "version": "1.0.0-1.19",
  "name": "Trident Fly",
  "description": "Cheat that alows always to fly on your trident",
  "authors": [
    "Butukay"
  ],
  "contact": {},
  "license": "MIT",
  "icon": "assets/trident-fly/icon.png",
  "environment": "client",
  "entrypoints": {
    "main": [
      "com.butukay.tridentfly.TridentFly"
    ]
  },
  "mixins": [
    "trident-fly.mixins.json"
  ],
  "depends": {
    "fabricloader": ">=0.14.6",
    "fabric": "*",
    "minecraft": "~1.19",
    "java": ">=17"
  },
  "custom": {
    "modmenu": {
      "links": { "modmenu.discord": "https://discord.gg/F7hCsM4RaF" },
      "badges": [ ],
      "parent": {
        "id": "tweaks",
        "name": "ButukayTweaks",
        "description": "Butukay's simple tweaks",
        "icon": "assets/trident-fly/parent-icon.png",
        "badges": []
      }
    }
  }
}
